npxpy/__init__.py
npxpy/_version.py
npxpy/gds.py
npxpy/preset.py
npxpy/resources.py
npxpy/images/__init__.py
npxpy/images/logo.png
npxpy/nodes/__init__.py
npxpy/nodes/_viewport_helpers.py
npxpy/nodes/aligners.py
npxpy/nodes/misc.py
npxpy/nodes/node.py
npxpy/nodes/project.py
npxpy/nodes/space.py
npxpy/nodes/structures.py
npxpy-0.4.0.dist-info/licenses/LICENSE
npxpy-0.4.0.dist-info/METADATA
npxpy-0.4.0.dist-info/WHEEL
npxpy-0.4.0.dist-info/top_level.txt
npxpy-0.4.0.dist-info/RECORD
