Metadata-Version: 2.4
Name: npxpy
Version: 0.4.0
Summary: Python based open source text-only project preparation framework for Nanoscribe's two-photon 3D lithography system Quantum X align.
Author: Caghan Ünlüer, Simone Ferrari, Wolfram Pernice
Project-URL: Bug Tracker, https://github.com/cuenlueer/npxpy/issues
Project-URL: Source Code, https://github.com/cuenlueer/npxpy
Project-URL: Documentation, https://cuenlueer.github.io/npxpy/
Classifier: Development Status :: 5 - Production/Stable
Classifier: Intended Audience :: Science/Research
Classifier: Topic :: Scientific/Engineering
Classifier: Topic :: Scientific/Engineering :: Physics
Classifier: Topic :: Scientific/Engineering :: Chemistry
Classifier: Topic :: Scientific/Engineering :: Medical Science Apps.
Classifier: Programming Language :: Python :: 3
Classifier: Programming Language :: Python :: 3.7
Classifier: Programming Language :: Python :: 3.8
Classifier: Programming Language :: Python :: 3.9
Classifier: Programming Language :: Python :: 3.10
Classifier: Programming Language :: Python :: 3.11
Classifier: License :: OSI Approved :: MIT License
Classifier: Operating System :: OS Independent
Requires-Python: >=3.7
License-File: LICENSE
Requires-Dist: pytomlpp
Requires-Dist: numpy-stl
Provides-Extra: all
Requires-Dist: pyvistaqt; extra == "all"
Requires-Dist: pyvista; extra == "all"
Requires-Dist: numpy; extra == "all"
Requires-Dist: PyQt5; extra == "all"
Requires-Dist: klayout; extra == "all"
Requires-Dist: shapely>=1.8.0; extra == "all"
Requires-Dist: trimesh[easy]; extra == "all"
Requires-Dist: pillow; extra == "all"
Provides-Extra: viewport
Requires-Dist: pyvistaqt; extra == "viewport"
Requires-Dist: pyvista; extra == "viewport"
Requires-Dist: numpy; extra == "viewport"
Requires-Dist: PyQt5; extra == "viewport"
Provides-Extra: gds
Requires-Dist: klayout; extra == "gds"
Requires-Dist: numpy; extra == "gds"
Requires-Dist: shapely>=1.8.0; extra == "gds"
Requires-Dist: trimesh[easy]; extra == "gds"
Requires-Dist: pillow; extra == "gds"
Dynamic: license-file
